[
  {
    "tags": [],
    "deleted": null,
    "query": "\"ntp.in_sync\".over(\"*\").last(2).count_by_status()",
    "message": "Triggers if any host's clock goes out of sync with the time given by NTP. The offset threshold is configured in the Agent's `ntp.yaml` file.\n\nPlease read the [KB article](https://docs.datadoghq.com/agent/faq/network-time-protocol-ntp-offset-issues) on NTP Offset issues for more details on cause and resolution.",
    "matching_downtimes": [],
    "id": 7985143,
    "multi": true,
    "name": "[Auto] Clock in sync with NTP",
    "created": "2019-01-17T21:29:24.482387+00:00",
    "created_at": 1547760564000,
    "creator": {
      "id": 1089397,
      "handle": "support-contrast-1",
      "name": "Datadog Support",
      "email": "support-user-prod@datadoghq.com"
    },
    "org_id": 238152,
    "modified": "2019-01-17T21:29:24.482387+00:00",
    "overall_state_modified": "2019-03-06T00:55:09.445913+00:00",
    "type": "service check",
    "options": {
      "thresholds": {
        "warning": 1,
        "ok": 1,
        "critical": 1
      },
      "silenced": {}
    }
  }
]
